[{"userid":"190958","movie_showid":8557,"food_id":null,"count_num":null,"showmovie_seatsss":["E3","E4","E1","E2"],"dynam_foodval":null,"movie_seatsss":["E3","E4","E1","E2"],"sess_seatrowid":"","seat_cat_type_id":"1","movie_amt":760,"foodvalue":0,"conv_fees":120,"three_d_charge":"0","transac_id":"20001305976","Cin_Id":"3","movieId":"HO00000326","movie_Name":"Valimai-Tamil","movie_Language":"TAMIL","movie_Censor":"U\/A","movie_Genre":"TAMIL","movie_runTime":178,"movie_location":"AGS VILLVAKKAM","movie_showtime":"11:00 AM","movie_date":"25-02-2022","movie_screen":"SCREEN 5","catcode":"0001","covid_confirm":"true"}]