[{"userid":"191630","movie_showid":7536,"food_id":null,"count_num":null,"showmovie_seatsss":["F10","F11"],"dynam_foodval":null,"movie_seatsss":["F10","F11"],"sess_seatrowid":"","seat_cat_type_id":"1","movie_amt":380,"foodvalue":0,"conv_fees":60,"three_d_charge":"0","transac_id":"20001264692","Cin_Id":"2","movieId":"HO00000362","movie_Name":"Hey Sinamika-Tamil","movie_Language":"TAMIL","movie_Censor":"U","movie_Genre":"TAMIL","movie_runTime":149,"movie_location":"AGS NAVALUR","movie_showtime":"12:00 PM","movie_date":"07-03-2022","movie_screen":"SCREEN 1","catcode":"0001","covid_confirm":null}]