[{"userid":"192509","movie_showid":9699,"food_id":null,"count_num":null,"showmovie_seatsss":["H16"],"dynam_foodval":null,"movie_seatsss":["H16"],"sess_seatrowid":"","seat_cat_type_id":"1","movie_amt":220,"foodvalue":0,"conv_fees":30,"three_d_charge":"0","transac_id":"20001672371","Cin_Id":"4","movieId":"HO00000322","movie_Name":"3D Rattham Ranam Rowthiram-Tamil","movie_Language":"TAMIL","movie_Censor":"U\/A","movie_Genre":"TAMIL","movie_runTime":187,"movie_location":"AGS ALAPAKKAM","movie_showtime":"3:00 PM","movie_date":"26-03-2022","movie_screen":"SCREEN 2","catcode":"0003","covid_confirm":"true"}]