[{"userid":"192045","movie_showid":7856,"food_id":null,"count_num":null,"showmovie_seatsss":["D6","D7"],"dynam_foodval":null,"movie_seatsss":["D6","D7"],"sess_seatrowid":"","seat_cat_type_id":"1","movie_amt":320,"foodvalue":0,"conv_fees":60,"three_d_charge":"0","transac_id":"20001030973","Cin_Id":"1","movieId":"HO00000373","movie_Name":"The Kashmir Files(Hindi-A)","movie_Language":"HINDI","movie_Censor":"A","movie_Genre":"HINDI","movie_runTime":170,"movie_location":"AGS TNAGAR","movie_showtime":"7:20 PM","movie_date":"18-03-2022","movie_screen":"SCREEN 2","catcode":"0001","covid_confirm":null}]