[{"userid":"25657","movie_showid":6929,"food_id":null,"count_num":null,"showmovie_seatsss":["C8","C9","C10","C11","C12"],"dynam_foodval":null,"movie_seatsss":["C8","C9","C10","C11","C12"],"sess_seatrowid":"","seat_cat_type_id":"1","movie_amt":1000,"foodvalue":0,"conv_fees":150,"three_d_charge":"0","transac_id":"20001219140","Cin_Id":"3","movieId":"HO00000295","movie_Name":"83-Hindi","movie_Language":"HINDI","movie_Censor":"U","movie_Genre":"HINDI","movie_runTime":162,"movie_location":"AGS VILLVAKKAM","movie_showtime":"3:45 PM","movie_date":"26-12-2021","movie_screen":"SCREEN 3","catcode":"0001","covid_confirm":"true"}]