[{"userid":"192310","movie_showid":9309,"food_id":null,"count_num":null,"showmovie_seatsss":["G7","G8"],"dynam_foodval":null,"movie_seatsss":["G7","G8"],"sess_seatrowid":"","seat_cat_type_id":"1","movie_amt":400,"foodvalue":0,"conv_fees":60,"three_d_charge":"0","transac_id":"20001634030","Cin_Id":"3","movieId":"HO00000321","movie_Name":"Rise Roar Revolt-Telugu","movie_Language":"TELUGU","movie_Censor":"U\/A","movie_Genre":"TELUGU","movie_runTime":187,"movie_location":"AGS VILLVAKKAM","movie_showtime":"11:05 AM","movie_date":"26-03-2022","movie_screen":"SCREEN 2","catcode":"0001","covid_confirm":"true"}]