[{"userid":"189627","movie_showid":6736,"food_id":["17","19","23"],"count_num":["1","1","1"],"showmovie_seatsss":["B2","B3","B1"],"dynam_foodval":"after","movie_seatsss":["B2","B3","B1"],"sess_seatrowid":"","seat_cat_type_id":"1","movie_amt":450,"foodvalue":350,"conv_fees":90,"three_d_charge":"0","transac_id":"20001213422","Cin_Id":"3","movieId":"HO00000253","movie_Name":"Maanaadu-Tamil","movie_Language":"TAMIL","movie_Censor":"U\/A","movie_Genre":"TAMIL","movie_runTime":147,"movie_location":"AGS VILLVAKKAM","movie_showtime":"1:00 PM","movie_date":"21-12-2021","movie_screen":"SCREEN 1","catcode":"0001","covid_confirm":"true"}]