[{"userid":"190075","movie_showid":7633,"food_id":null,"count_num":null,"showmovie_seatsss":["G18","G6","G8","G10","G14"],"dynam_foodval":null,"movie_seatsss":["G18","G6","G8","G10","G14"],"sess_seatrowid":"","seat_cat_type_id":"1","movie_amt":1200,"foodvalue":0,"conv_fees":150,"three_d_charge":"0","transac_id":"20001313445","Cin_Id":"4","movieId":"HO00000283","movie_Name":"Spider -Man:No Way home 3D-English","movie_Language":"ENGLISH","movie_Censor":"U\/A","movie_Genre":"ENGLISH","movie_runTime":148,"movie_location":"AGS ALAPAKKAM","movie_showtime":"12:50 PM","movie_date":"02-01-2022","movie_screen":"SCREEN 4","catcode":"0003","covid_confirm":"true"}]