[{"userid":"187116","movie_showid":4704,"food_id":null,"count_num":null,"showmovie_seatsss":["U7"],"dynam_foodval":null,"movie_seatsss":["U7"],"sess_seatrowid":"","seat_cat_type_id":"1","movie_amt":165,"foodvalue":0,"conv_fees":30,"three_d_charge":"0","transac_id":"20000844500","Cin_Id":"2","movieId":"HO00000224","movie_Name":"Dune-English","movie_Language":"ENGLISH","movie_Censor":"U\/A","movie_Genre":"ENGLISH","movie_runTime":155,"movie_location":"AGS NAVALUR","movie_showtime":"10:35 PM","movie_date":"31-10-2021","movie_screen":"SCREEN 1","catcode":"0001"}]