{"blnSuccess":true,"curTotal":600.0,"curTicketsTotal":600.0,"curFoodTotal":0.0,"curBookingFee":0.0,"intBookId":235134,"strBookingEx":"20000235134","strBookId":"W3ZQEEQ","strBookingStatus":null,"intException":0,"intExceptionEx":0,"strException":"","strSeatInfo":"DIAMOND - H10, H11, H12","strTempTransId":"20001053466","lngAuditNumber":222124,"strPrintData":null,"intPrintCount":0,"curTicketsTax":0.0,"curFoodTax":0.0,"curTicketsTax1":0.0,"curTicketsTax2":0.0,"curTicketsTax3":0.0,"curTicketsTax4":0.0,"curFoodTax1":0.0,"curFoodTax2":0.0,"curFoodTax3":0.0,"curFoodTax4":0.0,"strSplitBookingId":null}