{"status":1,"msg":"1 out of 1 Transactions Fetched Successfully","transaction_details":{"20000812865":{"mihpayid":"14477414122","request_id":"","bank_ref_num":"136418738235","amt":"690.00","transaction_amount":"690.00","txnid":"20000812865","additional_charges":"0.00","productinfo":"AGS_Cinemas 6002 M8 M9 M10","firstname":"Madhurika","bankcode":"VISA","udf1":null,"udf3":null,"udf4":null,"udf5":null,"field2":"738235","field9":"Success","error_code":"E000","addedon":"2021-12-30 18:25:51","payment_source":"payu","card_type":"VISA","error_Message":"NO ERROR","net_amount_debit":690,"disc":"0.00","mode":"DC","PG_TYPE":"DC-PG","card_no":"421436XXXXXX2275","name_on_card":"Tetali Satyanaraya","udf2":null,"status":"success","unmappedstatus":"captured","Merchant_UTR":null,"Settled_At":"0000-00-00 00:00:00"}}}