{"status":1,"msg":"1 out of 1 Transactions Fetched Successfully","transaction_details":{"20001698094":{"mihpayid":"14934649707","request_id":"","bank_ref_num":"208947817972","amt":"240.00","transaction_amount":"240.00","txnid":"20001698094","additional_charges":"0.00","productinfo":"AGS_Cinemas 9832 N1 N2","firstname":"Akash","bankcode":"UPI","udf1":null,"udf3":null,"udf4":null,"udf5":null,"field2":"208947817972","field9":"SUCCESS|Completed Using Verify API","error_code":"E000","addedon":"2022-03-30 10:11:02","payment_source":"payu","card_type":null,"error_Message":"NO ERROR","net_amount_debit":240,"disc":"0.00","mode":"UPI","PG_TYPE":"UPI-PG","card_no":"","udf2":null,"status":"success","unmappedstatus":"captured","Merchant_UTR":null,"Settled_At":"0000-00-00 00:00:00","App_Name":"GooglePay"}}}