{"status":1,"msg":"1 out of 1 Transactions Fetched Successfully","transaction_details":{"20000971770":{"mihpayid":"14802136395","request_id":"","bank_ref_num":"202206350085975","amt":"900.00","transaction_amount":"900.00","txnid":"20000971770","additional_charges":"0.00","productinfo":"AGS_Cinemas 7594 K7 K8","firstname":"Karthick","bankcode":"MAST","udf1":null,"udf3":null,"udf4":null,"udf5":null,"field2":"359520","field9":"success","error_code":"E000","addedon":"2022-03-04 18:46:02","payment_source":"payu","card_type":"MAST","error_Message":"NO ERROR","net_amount_debit":900,"disc":"0.00","mode":"DC","PG_TYPE":"DC-PG","card_no":"526099XXXXXX9070","name_on_card":"Karthick R","udf2":null,"status":"success","unmappedstatus":"captured","Merchant_UTR":null,"Settled_At":"0000-00-00 00:00:00"}}}