{"status":1,"msg":"1 out of 1 Transactions Fetched Successfully","transaction_details":{"20000804157":{"mihpayid":"14453054472","request_id":"","bank_ref_num":"20211225111212800110168177182223619","amt":"93.00","transaction_amount":"93.00","txnid":"20000804157","additional_charges":"0.00","productinfo":"AGS_Cinemas 5987 T8","firstname":"aleem","bankcode":"PAYTM","udf1":null,"udf3":null,"udf4":null,"udf5":null,"field2":"20211225111212800110168177182223619","field9":"Txn Success","error_code":"E000","addedon":"2021-12-25 17:51:24","payment_source":"payu","card_type":null,"error_Message":"NO ERROR","net_amount_debit":93,"disc":"0.00","mode":"CASH","PG_TYPE":"CASH-PG","card_no":"","udf2":null,"status":"success","unmappedstatus":"captured","Merchant_UTR":null,"Settled_At":"0000-00-00 00:00:00"}}}