{"status":1,"msg":"1 out of 1 Transactions Fetched Successfully","transaction_details":{"20000611747":{"mihpayid":"14204233007","request_id":"","bank_ref_num":"302542292","amt":"880.00","transaction_amount":"880.00","txnid":"20000611747","additional_charges":"0.00","productinfo":"AGS_Cinemas 4920 L4 L3 L2 L1","firstname":"sivakumar","bankcode":"CUBB","udf1":null,"udf3":null,"udf4":null,"udf5":null,"field2":null,"field9":"Transaction Completed Successfully","error_code":"E000","addedon":"2021-11-02 10:46:02","payment_source":"payu","card_type":null,"error_Message":"NO ERROR","net_amount_debit":880,"disc":"0.00","mode":"NB","PG_TYPE":"NB-PG","card_no":"","udf2":null,"status":"success","unmappedstatus":"captured","Merchant_UTR":null,"Settled_At":"0000-00-00 00:00:00"}}}