{"status":1,"msg":"1 out of 1 Transactions Fetched Successfully","transaction_details":{"20000931931":{"mihpayid":"14757873979","request_id":"","bank_ref_num":"205522507296","amt":"440.00","transaction_amount":"440.00","txnid":"20000931931","additional_charges":"0.00","productinfo":"AGS_Cinemas 7364 K3 K4","firstname":"Jaisaiarun","bankcode":"UPI","udf1":null,"udf3":null,"udf4":null,"udf5":null,"field2":"47470688280","field9":"SUCCESS|Completed Using Callback","error_code":"E000","addedon":"2022-02-24 10:28:06","payment_source":"payu","card_type":null,"error_Message":"NO ERROR","net_amount_debit":440,"disc":"0.00","mode":"UPI","PG_TYPE":"UPI-PG","card_no":"","udf2":null,"status":"success","unmappedstatus":"captured","Merchant_UTR":null,"Settled_At":"0000-00-00 00:00:00","App_Name":"PhonePe"}}}